ironflock/CrossbarConnection.py
ironflock/__init__.py
ironflock/ironflock.py
ironflock/types.py
ironflock-1.3.8.dist-info/METADATA
ironflock-1.3.8.dist-info/WHEEL
ironflock-1.3.8.dist-info/licenses/LICENSE
ironflock-1.3.8.dist-info/RECORD
