Metadata-Version: 2.4
Name: ironflock
Version: 1.3.8
Summary: IronFlock Python SDK for connecting to the IronFlock Platform
License-Expression: MIT
License-File: LICENSE
Author: Marko Petzold, IronFlock GmbH
Author-email: info@ironflock.com
Requires-Python: >=3.11
Classifier: Development Status :: 5 - Production/Stable
Classifier: Intended Audience :: Developers
Provides-Extra: dev
Provides-Extra: docs
Requires-Dist: autobahn[asyncio,serialization] (==25.10.2)
Requires-Dist: mypy ; extra == "dev"
Requires-Dist: pydantic (>=2.0.0)
Requires-Dist: pydantic ; extra == "dev"
Requires-Dist: pytest ; extra == "dev"
Requires-Dist: ruff ; extra == "dev"
Requires-Dist: sphinx (>=8.2.3) ; extra == "docs"
Requires-Dist: sphinx-autodoc-typehints (>=2.0) ; extra == "docs"
Requires-Dist: sphinx-book-theme (>=1.1.4) ; extra == "docs"
Project-URL: Homepage, https://github.com/RecordEvolution/ironflock-py
Project-URL: Repository, https://github.com/RecordEvolution/ironflock-py
